sample_notebooks/__init__.py
utilsds/Supervised.py
utilsds/__init__.py
utilsds/algorithm.py
utilsds/classifier.py
utilsds/confusion_matrix.py
utilsds/data_ops.py
utilsds/data_processing.py
utilsds/data_split.py
utilsds/ds_statistics.py
utilsds/evaluate.py
utilsds/experiments.py
utilsds/hyperopt.py
utilsds/metrics.py
utilsds/modeling.py
utilsds/monitoring.py
utilsds/transform_data.py
utilsds/visualization.py
utilsds/what_if_streamlit.py
utilsds-1.1.16.dist-info/METADATA
utilsds-1.1.16.dist-info/WHEEL
utilsds-1.1.16.dist-info/top_level.txt
utilsds-1.1.16.dist-info/RECORD
