Metadata-Version: 2.4
Name: utilsds
Version: 1.1.16
Summary: Solution for DS Team
Author: DS Team
Author-email: ds@sts.pl
Classifier: Programming Language :: Python :: 3
Classifier: License :: OSI Approved :: MIT License
Classifier: Operating System :: OS Independent
Requires-Python: >=3.11
Requires-Dist: pandas>=2.2.2
Requires-Dist: numpy<=2.1.0,>=1.26.4
Requires-Dist: scikit-learn>=1.4.2
Requires-Dist: seaborn>=0.13.2
Requires-Dist: matplotlib>=3.9.0
Requires-Dist: google-cloud-bigquery>=3.22.0
Requires-Dist: google-cloud-bigquery-storage>=2.0.0
Requires-Dist: google-cloud-storage>=2.16.0
Requires-Dist: google-cloud-aiplatform>=1.51.0
Requires-Dist: scipy>=1.13.0
Requires-Dist: hyperopt>=0.2.7
Requires-Dist: tqdm>=4.66.4
Requires-Dist: xgboost>=1.7.6
Requires-Dist: lightgbm>=4.0.0
Requires-Dist: yellowbrick>=1.5
Requires-Dist: cloudpickle>=2.3.0
Requires-Dist: db-dtypes>=1.4.0
Requires-Dist: pygments>=2.19.1
Requires-Dist: shap>=0.41.0
Requires-Dist: numba>=0.61.0
Requires-Dist: pandas-gbq>=0.26.1
Requires-Dist: jinja2>=3.1.3
Requires-Dist: setuptools>=75.8.0
Requires-Dist: evidently<0.6.7,>=0.4.39
Requires-Dist: ipython<=8.31.0
Requires-Dist: duckdb>=1.2.1
Dynamic: author
Dynamic: author-email
Dynamic: classifier
Dynamic: description
Dynamic: description-content-type
Dynamic: requires-dist
Dynamic: requires-python
Dynamic: summary
